atcb_eval/__init__.py
atcb_eval/benchmark.py
atcb_eval/cli.py
atcb_eval/evaluator.py
atcb_eval/metrics.py
atcb_eval/types.py
atcb_eval-0.1.0.dist-info/licenses/LICENSE
atcb_eval-0.1.0.dist-info/METADATA
atcb_eval-0.1.0.dist-info/WHEEL
atcb_eval-0.1.0.dist-info/entry_points.txt
atcb_eval-0.1.0.dist-info/top_level.txt
atcb_eval-0.1.0.dist-info/RECORD
