Metadata-Version: 2.4
Name: atcb-eval
Version: 0.1.0
Summary: Agent Tool-Use Calibration Benchmark - Evaluate if AI agents know when they'll fail
Author-email: Debu Sinha <debusinha2009@gmail.com>
Maintainer-email: Debu Sinha <debusinha2009@gmail.com>
License-Expression: MIT
Project-URL: Homepage, https://github.com/debu-sinha/atcb-benchmark
Project-URL: Documentation, https://github.com/debu-sinha/atcb-benchmark#readme
Project-URL: Repository, https://github.com/debu-sinha/atcb-benchmark
Project-URL: Issues, https://github.com/debu-sinha/atcb-benchmark/issues
Project-URL: Changelog, https://github.com/debu-sinha/atcb-benchmark/blob/main/CHANGELOG.md
Keywords: ai-agents,calibration,tool-use,llm-evaluation,uncertainty-quantification,benchmark,ai-safety,expected-calibration-error,reliability-diagrams
Classifier: Development Status :: 4 - Beta
Classifier: Intended Audience :: Science/Research
Classifier: Intended Audience :: Developers
Classifier: Operating System :: OS Independent
Classifier: Programming Language :: Python :: 3
Classifier: Programming Language :: Python :: 3.8
Classifier: Programming Language :: Python :: 3.9
Classifier: Programming Language :: Python :: 3.10
Classifier: Programming Language :: Python :: 3.11
Classifier: Programming Language :: Python :: 3.12
Classifier: Topic :: Scientific/Engineering :: Artificial Intelligence
Classifier: Topic :: Software Development :: Libraries :: Python Modules
Classifier: Typing :: Typed
Requires-Python: >=3.8
License-File: LICENSE
Requires-Dist: numpy>=1.20.0
Provides-Extra: openai
Requires-Dist: openai>=1.0.0; extra == "openai"
Provides-Extra: anthropic
Requires-Dist: anthropic>=0.18.0; extra == "anthropic"
Provides-Extra: google
Requires-Dist: google-generativeai>=0.3.0; extra == "google"
Provides-Extra: all
Requires-Dist: openai>=1.0.0; extra == "all"
Requires-Dist: anthropic>=0.18.0; extra == "all"
Requires-Dist: google-generativeai>=0.3.0; extra == "all"
Provides-Extra: dev
Requires-Dist: pytest>=7.0.0; extra == "dev"
Requires-Dist: pytest-cov>=4.0.0; extra == "dev"
Requires-Dist: pytest-asyncio>=0.21.0; extra == "dev"
Requires-Dist: black>=23.0.0; extra == "dev"
Requires-Dist: ruff>=0.1.0; extra == "dev"
Requires-Dist: mypy>=1.0.0; extra == "dev"
Requires-Dist: pre-commit>=3.0.0; extra == "dev"
Provides-Extra: viz
Requires-Dist: matplotlib>=3.5.0; extra == "viz"
Requires-Dist: seaborn>=0.12.0; extra == "viz"
Provides-Extra: docs
Requires-Dist: mkdocs>=1.5.0; extra == "docs"
Requires-Dist: mkdocs-material>=9.0.0; extra == "docs"
Requires-Dist: mkdocstrings[python]>=0.24.0; extra == "docs"
Dynamic: license-file
